fdog/__init__.py
fdog/addTaxa.py
fdog/addTaxon.py
fdog/checkData.py
fdog/mergeOutput.py
fdog/removefDog.py
fdog/runMulti.py
fdog/runSingle.py
fdog/setPaths.py
fdog/setupfDog.py
fdog/showTaxa.py
fdog/data/__init__.py
fdog/data/conda_requirements.yml
fdog/data/dependencies.txt
fdog/data/infile.fa
fdog/libs/__init__.py
fdog/libs/addtaxon.py
fdog/libs/alignment.py
fdog/libs/blast.py
fdog/libs/corecompile.py
fdog/libs/fas.py
fdog/libs/fasta.py
fdog/libs/hmm.py
fdog/libs/orthosearch.py
fdog/libs/output.py
fdog/libs/preparation.py
fdog/libs/tree.py
fdog/libs/zzz.py
fdog-1.0.0.dist-info/licenses/LICENSE
fdog-1.0.0.dist-info/METADATA
fdog-1.0.0.dist-info/WHEEL
fdog-1.0.0.dist-info/entry_points.txt
fdog-1.0.0.dist-info/top_level.txt
fdog-1.0.0.dist-info/RECORD
